weni_cli/__init__.py
weni_cli/auth.py
weni_cli/cli.py
weni_cli/clients/__init__.py
weni_cli/clients/cli_client.py
weni_cli/clients/common.py
weni_cli/clients/response_handlers/__init__.py
weni_cli/clients/response_handlers/handlers.py
weni_cli/clients/tests/__init__.py
weni_cli/clients/tests/test_cli_client.py
weni_cli/clients/tests/test_weni_client.py
weni_cli/clients/weni_client.py
weni_cli/commands/channel_create.py
weni_cli/commands/init.py
weni_cli/commands/login.py
weni_cli/commands/logs.py
weni_cli/commands/project_current.py
weni_cli/commands/project_list.py
weni_cli/commands/project_push.py
weni_cli/commands/project_use.py
weni_cli/commands/run.py
weni_cli/formatter/__init__.py
weni_cli/formatter/formatter.py
weni_cli/formatter/tests/test_formatter.py
weni_cli/handler.py
weni_cli/packager/__init__.py
weni_cli/packager/packager.py
weni_cli/packager/tests/__init__.py
weni_cli/packager/tests/test_packager.py
weni_cli/spinner/__init__.py
weni_cli/spinner/spinners.py
weni_cli/store.py
weni_cli/utils.py
weni_cli/validators/__init__.py
weni_cli/validators/agent_definition.py
weni_cli/validators/channel_definition.py
weni_cli/validators/tests/__init__.py
weni_cli/validators/tests/test_channel_definition.py
weni_cli/validators/tests/test_definition.py
weni_cli/wsgi.py
weni_cli-3.5.0.dist-info/METADATA
weni_cli-3.5.0.dist-info/WHEEL
weni_cli-3.5.0.dist-info/entry_points.txt
weni_cli-3.5.0.dist-info/RECORD
