Metadata-Version: 2.1
Name: weni-cli
Version: 3.5.0
Summary: 
Author: Paulo Bernardo
Author-email: paulo.bernardo@weni.ai
Requires-Python: >=3.10,<4.0
Classifier: Programming Language :: Python :: 3
Classifier: Programming Language :: Python :: 3.10
Classifier: Programming Language :: Python :: 3.11
Classifier: Programming Language :: Python :: 3.12
Classifier: Programming Language :: Python :: 3.13
Requires-Dist: click (>=8.1.8,<9.0.0)
Requires-Dist: flask (>=3.1.1,<4.0.0)
Requires-Dist: python-slugify (>=8.0.4,<9.0.0)
Requires-Dist: pyyaml (>=6.0.2,<7.0.0)
Requires-Dist: regex (>=2024.11.6,<2025.0.0)
Requires-Dist: requests (>=2.32.3,<3.0.0)
Requires-Dist: rich (>=13.9.4,<14.0.0)
Requires-Dist: rich-click (>=1.8.6,<2.0.0)
Requires-Dist: waitress (>=3.0.2,<4.0.0)
Requires-Dist: weni-agents-toolkit (==2.3.2)
